hiddenprint/__init__.py
hiddenprint/hiddenprints.py
hiddenprint-0.0.2.dist-info/METADATA
hiddenprint-0.0.2.dist-info/WHEEL
hiddenprint-0.0.2.dist-info/licenses/LICENSE
hiddenprint-0.0.2.dist-info/RECORD
