Metadata-Version: 2.3
Name: HiddenPrint
Version: 0.0.2
Summary: A small package to block print statements
Project-URL: Homepage, https://github.com/AdmiralLuke/HiddenPrints
Project-URL: Issues, https://github.com/AdmiralLuke/HiddenPrints/issues
Author: Luke
License-File: LICENSE
Classifier: License :: OSI Approved :: MIT License
Classifier: Operating System :: OS Independent
Classifier: Programming Language :: Python :: 3
Requires-Python: >=3.8
